repoze.who-3.1.0-py3.12-nspkg.pth
repoze/who/_auth_tkt.py
repoze/who/_helpers.py
repoze/who/api.py
repoze/who/classifiers.py
repoze/who/config.py
repoze/who/interfaces.py
repoze/who/middleware.py
repoze/who/restrict.py
repoze/who/utils.py
repoze/who/plugins/auth_tkt.py
repoze/who/plugins/basicauth.py
repoze/who/plugins/htpasswd.py
repoze/who/plugins/redirector.py
repoze/who/plugins/sql.py
repoze/who/plugins/tests/__init__.py
repoze/who/plugins/tests/test_authtkt.py
repoze/who/plugins/tests/test_basicauth.py
repoze/who/plugins/tests/test_htpasswd.py
repoze/who/plugins/tests/test_redirector.py
repoze/who/plugins/tests/test_sql.py
repoze/who/plugins/tests/fixtures/__init__.py
repoze/who/plugins/tests/fixtures/test.htpasswd
repoze/who/tests/__init__.py
repoze/who/tests/test__auth_tkt.py
repoze/who/tests/test__helpers.py
repoze/who/tests/test_api.py
repoze/who/tests/test_classifiers.py
repoze/who/tests/test_config.py
repoze/who/tests/test_middleware.py
repoze/who/tests/test_restrict.py
repoze.who-3.1.0.dist-info/LICENSE.txt
repoze.who-3.1.0.dist-info/METADATA
repoze.who-3.1.0.dist-info/WHEEL
repoze.who-3.1.0.dist-info/entry_points.txt
repoze.who-3.1.0.dist-info/namespace_packages.txt
repoze.who-3.1.0.dist-info/top_level.txt
repoze.who-3.1.0.dist-info/RECORD
